genalpy/__init__.py
genalpy/chromosome.py
genalpy/genetic_algorithm.py
genalpy/population.py
genalpy/utils.py
genalpy-0.1.4.dist-info/METADATA
genalpy-0.1.4.dist-info/WHEEL
genalpy-0.1.4.dist-info/top_level.txt
genalpy-0.1.4.dist-info/RECORD
