Metadata-Version: 2.1
Name: genalpy
Version: 0.1.4
Summary: Genetic algorithms library
Home-page: https://genalpy-lib.readthedocs.io/en/latest/
Author: Mariia Kryvets
Author-email: mkrivets1@email.com
License: MIT
Platform: UNKNOWN
Classifier: Intended Audience :: Developers
Classifier: License :: OSI Approved :: MIT License
Classifier: Programming Language :: Python
Classifier: Programming Language :: Python :: 3
Classifier: Programming Language :: Python :: 3.6
Classifier: Programming Language :: Python :: 3.7
Classifier: Programming Language :: Python :: 3.8
Classifier: Programming Language :: Python :: 3.9
Classifier: Operating System :: OS Independent
Requires-Dist: numpy
Requires-Dist: pandas
